LICENCE
README.md
setup.py
pymcure/__init__.py
pymcure.egg-info/PKG-INFO
pymcure.egg-info/SOURCES.txt
pymcure.egg-info/dependency_links.txt
pymcure.egg-info/not-zip-safe
pymcure.egg-info/requires.txt
pymcure.egg-info/top_level.txt
pymcure/client/__init__.py
pymcure/client/exceptions.py
pymcure/client/message.py
pymcure/client/publisher/__init__.py
pymcure/client/publisher/asynch.py
pymcure/client/publisher/publisher.py
pymcure/client/publisher/sync.py
pymcure/client/publisher/tests/__init__.py
pymcure/client/publisher/tests/test_base.py
pymcure/client/subscriber/__init__.py
pymcure/client/subscriber/subscriber.py