Metadata-Version: 2.1
Name: pymcure
Version: 0.0.1.1.3
Summary: UNKNOWN
Home-page: https://github.com/Ouleur/Pymcure
Author: Vianney ADOU
License: MIT
Platform: any
Classifier: Environment :: Web Environment
Classifier: Intended Audience :: Developers
Classifier: Programming Language :: Python
Classifier: Programming Language :: Python :: 3
Classifier: License :: OSI Approved :: MIT License
Classifier: Operating System :: OS Independent
Classifier: Topic :: Internet :: WWW/HTTP :: Dynamic Content
Classifier: Topic :: Software Development :: Libraries :: Python Modules
License-File: LICENCE
